{
	"name": "Король",
	"description": "Генерирует короны, на которые можно покупать и улучшать фигуры.\n\n[b]Хар-ки на 1 уровне[/b]\nЦена: 100\nХиты: 1\nОткат генерации: 10\nГенеририует корон: 25",
	"side_text": ["Король не воздействует на другие сущности", "Король может переместиться на 1 клетку в любую сторону"],
	"counterattack": false,
	"max_count": 1,
	
	"skillbox": {},
	"move": {
		"Vector2(1, 1)": 1, "Vector2(1, 0)": 1, "Vector2(1, -1)": 1,
		 "Vector2(0, -1)": 1, "Vector2(-1, -1)": 1, "Vector2(-1, 0)": 1,
		 "Vector2(-1, 1)": 1, "Vector2(0, 1)": 1
	},
	
	"level1": {"cost": 100, "hits": 1, "crown": 25, "cooldown": 10},
	"level2": {"cost": 200, "hits": 1, "crown": 50, "cooldown": 10},
	"level3": {"cost": 350, "hits": 2, "crown": 50, "cooldown": 8},
	"level4": {"cost": 600, "hits": 2, "crown": 75, "cooldown": 8},
	"level5": {"cost": 850, "hits": 3, "crown": 100, "cooldown": 6}
}
